papylio/__init__.py
papylio/__main__.py
papylio/_version.py
papylio/autoconfig.py
papylio/background_subtraction.py
papylio/coordinate_optimization.py
papylio/decorators.py
papylio/default_configuration.yml
papylio/experiment.py
papylio/file.py
papylio/file_collection.py
papylio/log_functions.py
papylio/logo.png
papylio/molecule.py
papylio/netcdf_operations.py
papylio/peak_finding.py
papylio/plotting.py
papylio/plugin_manager.py
papylio/timer.py
papylio/trace_correction.py
papylio/trace_extraction.py
papylio/trace_plot.py
papylio/analysis/autoThreshold.py
papylio/analysis/classification_simple.py
papylio/analysis/dwell_time_analysis.py
papylio/analysis/dwell_time_extraction.py
papylio/analysis/hidden_markov_modelling.py
papylio/gui/icon.ico
papylio/gui/icon.png
papylio/gui/main.py
papylio/gui/selection_widget.py
papylio/gui/start.py
papylio/movie/background_correction.py
papylio/movie/basic_shading_correction.py
papylio/movie/binary.py
papylio/movie/movie.py
papylio/movie/nd2.py
papylio/movie/nsk.py
papylio/movie/pma.py
papylio/movie/shading_correction.py
papylio/movie/sifx.py
papylio/movie/tif.py
papylio/plugins/__init__.py
papylio/plugins/holliday_junction/basepairing_graph.py
papylio/plugins/holliday_junction/energies.py
papylio/plugins/holliday_junction/holliday_junction.py
papylio/plugins/holliday_junction/sequence_generation.py
papylio/plugins/holliday_junction/sequence_properties.py
papylio/plugins/sequencing/Example.py
papylio/plugins/sequencing/__init__.py
papylio/plugins/sequencing/fastqAnalysis.py
papylio/plugins/sequencing/geometricHashing2.py
papylio/plugins/sequencing/geometricHashing3.py
papylio/plugins/sequencing/mapping_collection.py
papylio/plugins/sequencing/plotting.py
papylio/plugins/sequencing/sequence_generation.py
papylio/plugins/sequencing/sequence_plotting.py
papylio/plugins/sequencing/sequencing.py
papylio/plugins/sequencing/sequencing_data.py
papylio-0.9.1.dist-info/licenses/LICENSE
papylio-0.9.1.dist-info/METADATA
papylio-0.9.1.dist-info/WHEEL
papylio-0.9.1.dist-info/top_level.txt
papylio-0.9.1.dist-info/RECORD
