Metadata-Version: 2.4
Name: papylio
Version: 0.9.1
Summary: Single-molecule fluorescence data extraction and analysis.
Author-email: Ivo Severins <i.w.h.severins@tudelft.nl>
Project-URL: Documentation, https://papylio.readthedocs.io/
Project-URL: Repository, https://github.com/Chirlmin-Joo-lab/papylio
Keywords: single,molecule,trace,analysis,fluorescence,FRET
Classifier: Programming Language :: Python
Classifier: Programming Language :: Python :: 3
Classifier: License :: OSI Approved :: GNU General Public License v3 (GPLv3)
Requires-Python: <3.10,>=3.9
License-File: LICENSE
Requires-Dist: numpy<1.23,>=1.22.4
Requires-Dist: matplotlib<3.6,>=3.5
Requires-Dist: pathlib2>=2.3
Requires-Dist: opencv-python<4.6,>=4.5
Requires-Dist: tabulate<0.9,>=0.8
Requires-Dist: scipy<1.9,>=1.8
Requires-Dist: scikit-image<0.20,>=0.19
Requires-Dist: scikit-learn<1.1,>=1.0
Requires-Dist: pyyaml<6.1,>=6.0
Requires-Dist: pandas<1.5,>=1.4
Requires-Dist: seaborn<0.12,>=0.11
Requires-Dist: openpyxl<3.1,>=3.0
Requires-Dist: nd2reader<3.4,>=3.3
Requires-Dist: xarray<2023.2,>=2023.1
Requires-Dist: netcdf4<1.7,>=1.6
Requires-Dist: h5netcdf<1.1,>=1.0
Requires-Dist: dask<2024.2,>=2023.1
Requires-Dist: dask-image<2022.0,>=2021.12
Requires-Dist: bottleneck<1.4,>=1.3
Requires-Dist: tifffile<2022.11,>=2022.10.10
Requires-Dist: tqdm>=4.63
Requires-Dist: pyside2<5.16,>=5.13
Requires-Dist: numba<0.57,>=0.56
Requires-Dist: pomegranate==0.14.8; sys_platform == "win32"
Requires-Dist: pomegranate==0.15; sys_platform != "win32"
Requires-Dist: matchpoint<1.1,>=1.0.4
Requires-Dist: objectlist<1.1,>=1.0
Provides-Extra: sparxs
Requires-Dist: matplotlib-venn==0.11; extra == "sparxs"
Requires-Dist: perl; extra == "sparxs"
Provides-Extra: gui
Provides-Extra: dev
Requires-Dist: pytest; extra == "dev"
Requires-Dist: pytest-datadir; extra == "dev"
Requires-Dist: build; extra == "dev"
Requires-Dist: twine; extra == "dev"
Requires-Dist: sphinx; extra == "dev"
Requires-Dist: sphinx-book-theme; extra == "dev"
Requires-Dist: setuptools_scm>=8; extra == "dev"
Dynamic: license-file
